LICENSE.BAYKIT
README.md
setup.py
bayserver_core/__init__.py
bayserver_core/bay_dockers.py
bayserver_core/bay_exception.py
bayserver_core/bay_log.py
bayserver_core/bay_message.py
bayserver_core/bayserver.py
bayserver_core/config_exception.py
bayserver_core/http_exception.py
bayserver_core/mem_usage.py
bayserver_core/sink.py
bayserver_core/symbol.py
bayserver_core/version.py
bayserver_core.egg-info/PKG-INFO
bayserver_core.egg-info/SOURCES.txt
bayserver_core.egg-info/dependency_links.txt
bayserver_core.egg-info/top_level.txt
bayserver_core/agent/__init__.py
bayserver_core/agent/accept_handler.py
bayserver_core/agent/command_receiver.py
bayserver_core/agent/grand_agent.py
bayserver_core/agent/lifecycle_listener.py
bayserver_core/agent/next_socket_action.py
bayserver_core/agent/non_blocking_handler.py
bayserver_core/agent/spin_handler.py
bayserver_core/agent/timer_handler.py
bayserver_core/agent/upgrade_exception.py
bayserver_core/agent/letters/__init__.py
bayserver_core/agent/letters/accepted_letter.py
bayserver_core/agent/letters/closed_letter.py
bayserver_core/agent/letters/connected_letter.py
bayserver_core/agent/letters/error_letter.py
bayserver_core/agent/letters/letter.py
bayserver_core/agent/letters/read_letter.py
bayserver_core/agent/letters/wrote_letter.py
bayserver_core/agent/monitor/__init__.py
bayserver_core/agent/monitor/grand_agent_monitor.py
bayserver_core/agent/multiplexer/__init__.py
bayserver_core/agent/multiplexer/job_multiplexer.py
bayserver_core/agent/multiplexer/job_multiplexer_base.py
bayserver_core/agent/multiplexer/multiplexer_base.py
bayserver_core/agent/multiplexer/plain_transporter.py
bayserver_core/agent/multiplexer/secure_transporter.py
bayserver_core/agent/multiplexer/spider_multiplexer.py
bayserver_core/agent/multiplexer/spin_multiplexer.py
bayserver_core/agent/multiplexer/taxi_multiplexer.py
bayserver_core/agent/multiplexer/write_unit.py
bayserver_core/agent/signal/__init__.py
bayserver_core/agent/signal/signal_agent.py
bayserver_core/agent/signal/signal_proxy.py
bayserver_core/agent/signal/signal_sender.py
bayserver_core/agent/transporter/__init__.py
