Metadata-Version: 1.2
Name: bayserver-core
Version: 3.0.0
Summary: BayServer core module
Home-page: https://baykit.yokohama/
Author: Michisuke-P
Author-email: michisukep@gmail.com
License: MIT
Platform: UNKNOWN
Requires-Python: >=3.7
